magneto/__init__.py
magneto/basic_matcher.py
magneto/bp_reranker.py
magneto/column_encoder.py
magneto/embedding_matcher.py
magneto/llm_reranker.py
magneto/magneto.py
magneto/retriever.py
magneto/utils/__init__.py
magneto/utils/base_column.py
magneto/utils/base_table.py
magneto/utils/constants.py
magneto/utils/dataframe_column.py
magneto/utils/dataframe_table.py
magneto/utils/embedding_utils.py
magneto/utils/retriever_utils.py
magneto/utils/utils.py
magneto_python-0.2.0.dist-info/METADATA
magneto_python-0.2.0.dist-info/WHEEL
magneto_python-0.2.0.dist-info/top_level.txt
magneto_python-0.2.0.dist-info/RECORD
