Metadata-Version: 2.1
Name: magneto-python
Version: 0.2.0
Summary: Magneto Python library
Home-page: https://github.com/VIDA-NYU/data-integration-eval/tree/main/algorithms/magneto
Author: Yurong Liu, Eduardo Pena, Eden Wu, Aécio Santos, Roque Lopez
Author-email: yurong.liu@nyu.edu, em5487@nyu.edu, eden.wu@nyu.edu, aecio.santos@nyu.edu, rlopez@nyu.edu
Maintainer: 
Maintainer-email: 
License: Apache-2.0
Keywords: bdf,data integration,nyu
Classifier: Development Status :: 5 - Production/Stable
Classifier: Intended Audience :: Science/Research
Classifier: License :: OSI Approved :: Apache Software License
Classifier: Topic :: Scientific/Engineering
Requires-Python: >=3.9
Requires-Dist: pandas
Requires-Dist: openai
Requires-Dist: transformers
Requires-Dist: torch>=2.3.1
Requires-Dist: valentine
Requires-Dist: fuzzywuzzy
Requires-Dist: mmh3
Requires-Dist: scikit-learn
Requires-Dist: sentence-transformers
Requires-Dist: tiktoken
Requires-Dist: json-repair
Requires-Dist: litellm
